l2r/__init__.py
l2r/build.py
l2r/constants.py
l2r/core/__init__.py
l2r/core/classes.py
l2r/core/interfaces.py
l2r/core/templates.py
l2r/env/__init__.py
l2r/env/controller.py
l2r/env/env.py
l2r/env/reward.py
l2r/env/tracker.py
l2r/track/__init__.py
l2r/track/anglesey/AngleseyFromGoogle.json
l2r/track/data.py
l2r/track/racetrack.py
l2r/track/thruxton/ThruxtonFromGoogle_2.json
l2r/track/thruxton/ThruxtonOfficial.json
l2r/track/utils.py
l2r/utils/__init__.py
l2r/utils/space.py
l2r/utils/wrapper.py
l2r-0.0.2.dist-info/LICENSE
l2r-0.0.2.dist-info/WHEEL
l2r-0.0.2.dist-info/METADATA
l2r-0.0.2.dist-info/RECORD
