Metadata-Version: 2.1
Name: l2r
Version: 0.0.2
Summary: a OpenAI gym environment for high performance autonomous racing
Home-page: https://github.com/learn-to-race/l2r
License: MIT
Keywords: reinforcement learning,racing,robotics,machine learning,computer vision
Author: Jimmy Herman
Author-email: jimmyherman29@gmail.com
Requires-Python: >=3.7,<4.0
Classifier: License :: OSI Approved :: MIT License
Classifier: Programming Language :: Python :: 3
Classifier: Programming Language :: Python :: 3.7
Classifier: Programming Language :: Python :: 3.8
Classifier: Programming Language :: Python :: 3.9
Classifier: Programming Language :: Python :: 3.10
Requires-Dist: Pillow (>=7.2.0,<8.0.0)
Requires-Dist: PyYAML (>=6.0,<7.0)
Requires-Dist: gast (>=0.5,<0.6)
Requires-Dist: gym (>=0.22,<0.23)
Requires-Dist: matplotlib (>=3.4,<4.0)
Requires-Dist: numpy (>=1.21,<2.0)
Requires-Dist: pyzmq (>=19.0,<20.0)
Requires-Dist: requests (>=2.18,<3.0)
Requires-Dist: scipy (>=1.6,<2.0)
Requires-Dist: tqdm (>=4.64,<5.0)
Requires-Dist: websocket_client (>=1.3,<2.0)
Project-URL: Repository, https://github.com/learn-to-race/l2r
